cubids/__about__.py
cubids/__init__.py
cubids/_version.py
cubids/cli.py
cubids/config.py
cubids/constants.py
cubids/cubids.py
cubids/metadata_merge.py
cubids/utils.py
cubids/validator.py
cubids/workflows.py
cubids/data/config.yml
cubids/data/references.bib
cubids/data/schema.json
cubids/tests/coverage.cfg
cubids/tests/test_apply.py
cubids/tests/test_bond.py
cubids/tests/test_cli.py
cubids/tests/test_cubids.py
cubids/tests/test_variants.py
cubids/tests/utils.py
cubids-1.2.0.dist-info/METADATA
cubids-1.2.0.dist-info/WHEEL
cubids-1.2.0.dist-info/entry_points.txt
cubids-1.2.0.dist-info/licenses/AUTHORS.rst
cubids-1.2.0.dist-info/licenses/LICENSE
cubids-1.2.0.dist-info/RECORD
